event_logger/__init__.py
event_logger/py.typed
event_logger-999999.0.0.dist-info/LICENSE
event_logger-999999.0.0.dist-info/WHEEL
event_logger-999999.0.0.dist-info/METADATA
event_logger-999999.0.0.dist-info/RECORD
